Metadata-Version: 1.0
Name: collection-pipelines
Version: 0.1.1
Summary: Framework to implement collection pipelines in python.
Home-page: https://github.com/povilasb/pycollection-pipelines
Author: Povilas Balciunas
Author-email: balciunas90@gmail.com
License: MIT
Platform: UNKNOWN
